{"is_source_file": true, "format": "JavaScript/TypeScript", "description": "This file contains Backbone.js models, collections, views, and router for a Todo application, including class definitions for Todo, TodoList, TodoView, TodoRouter, and AppView, along with application initialization code.", "external_files": ["underscore.js", "backbone.js", "jquery.js", "Store.js"], "external_methods": ["_.template", "_.bindAll", "Backbone.Model", "Backbone.Collection", "Backbone.View", "Backbone.Router", "Backbone.history.start", "$.ready"], "published": ["Todo", "TodoList", "Todos", "TodoView", "TodoRouter", "AppView"], "classes": [{"name": "Todo", "description": "Model representing a single todo item with default attributes, toggle, initialize, and clear methods."}, {"name": "TodoList", "description": "Collection of Todo models backed by localStorage, with methods for filtering and sorting."}, {"name": "TodoView", "description": "View for individual todo items, handling rendering, editing, toggling, and removal."}, {"name": "TodoRouter", "description": "Router managing filter routes for the todo list."}, {"name": "AppView", "description": "Top-level view managing the overall application UI, including rendering, event handling, and initializing the router."}], "methods": [{"name": "defaults", "description": "Returns default attributes for a Todo model."}, {"name": "initialize", "description": "Initializes a Todo model, ensuring it has a title."}, {"name": "toggle", "description": "Toggles the completed state of a Todo."}, {"name": "clear", "description": "Removes the Todo from storage."}, {"name": "completed", "description": "Filters the collection for completed todos."}, {"name": "remaining", "description": "Filters the collection for remaining todos."}, {"name": "nextOrder", "description": "Calculates the next order number for new todos."}, {"name": "comparator", "description": "Defines sorting order based on 'order' attribute."}, {"name": "render", "description": "Renders the individual Todo item view."}, {"name": "toggleDone", "description": "Toggles the completed state of the model."}, {"name": "toggleVisible", "description": "Shows or hides the Todo view based on filter."}, {"name": "edit", "description": "Switches the view into editing mode."}, {"name": "close", "description": "Saves or removes the Todo based on input."}, {"name": "updateOnEnter", "description": "Handles Enter key to save changes."}, {"name": "revertOnEscape", "description": "Reverts changes on Escape key."}, {"name": "clear", "description": "Destroys the Todo model."}, {"name": "setFilter", "description": "Sets the current filter for the Todo list."}, {"name": "render", "description": "Renders the overall app UI, including stats and filters."}, {"name": "addOne", "description": "Adds a single Todo item view to the list."}, {"name": "addAll", "description": "Adds all Todo items to the list."}, {"name": "filter", "description": "Sets the current filter criteria."}, {"name": "filterOne", "description": "Triggers visibility update for a Todo."}, {"name": "filterAll", "description": "Applies filter to all Todos."}, {"name": "newAttributes", "description": "Creates attributes for a new Todo."}, {"name": "createOnEnter", "description": "Creates a new Todo on Enter key press."}, {"name": "clearCompleted", "description": "Removes all completed Todos."}, {"name": "toggleAllComplete", "description": "Marks all Todos as completed or active."}], "calls": ["_.template", "_.bindAll", "this.model.bind", "this.model.toggle", "this.model.destroy", "Todos.trigger", "Todos.each", "Todos.create", "Backbone.history.start", "$('.todoapp')", "$('.new-todo')", "$('.toggle-all')", "$('.main')", "$('.footer')", "$('.todo-stats')", "$('.filters li a')", "$('.todo-list')", "_.each"], "search-terms": ["Backbone.js", "Todo MVC", "TypeScript Backbone", "app.js", "Todo Model", "Todo Collection", "Todo View", "Router", "localStorage"], "state": 2, "ctags": [], "filename": "examples/typescript-backbone/js/app.js", "format-version": 4, "code-base-name": "https://github.com/Kishore6753/todomvc.git:master", "knowledge_revision": 1044, "git_revision": "0f179593988f329e9288687364cb408f55b1b914", "revision_history": [{"1044": "0f179593988f329e9288687364cb408f55b1b914"}, {"1044": "0f179593988f329e9288687364cb408f55b1b914"}], "file_id": 492}