{"is_source_file": true, "format": "JavaScript", "description": "Defines a custom web component 'todo-topbar' for a Todo MVC application, managing the top bar UI including item counts, toggle all, and adding new items.", "external_files": ["./todo-topbar.template.js", "../../hooks/useKeyListener.js", "../../utils/nanoid.js", "../../../styles/global.constructable.js", "../../../styles/topbar.constructable.js"], "external_methods": ["useKeyListener", "nanoid"], "published": ["TodoTopbar"], "classes": [{"name": "TodoTopbar", "description": "A custom HTML element managing the top bar of a Todo list, handling display updates, event listeners, and user interactions."}], "methods": [{"name": "toggleAll", "description": "Dispatches a 'toggle-all' event with the completed status based on the toggle input."}, {"name": "addItem", "description": "Dispatches an 'add-item' event with a new item's id, title, and completion status."}, {"name": "updateDisplay", "description": "Updates the toggle input and container visibility based on current item counts and route."}, {"name": "updateRoute", "description": "Sets the current route and updates the display accordingly."}, {"name": "addListeners", "description": "Adds event listeners for toggle input and key listeners."}, {"name": "removeListeners", "description": "Removes event listeners for toggle input and key listeners."}, {"name": "attributeChangedCallback", "description": "Handles attribute changes and updates display if connected."}, {"name": "connectedCallback", "description": "Initializes key listeners, updates display, adds event listeners, and focuses input when component is added to DOM."}, {"name": "disconnectedCallback", "description": "Removes event listeners and clears key listeners when component is removed from DOM."}], "calls": ["document.importNode", "this.shadow.attachShadow", "this.shadow.adoptedStyleSheets", "this.shadow.append", "this.dispatchEvent", "new CustomEvent", "parseInt", "useKeyListener", "this.todoInput.focus"], "search-terms": ["todo-topbar", "custom element", "toggle all", "add item", "item counts", "web component", "shadow DOM", "topbar"], "state": 2, "ctags": [], "filename": "examples/web-components/src/components/todo-topbar/todo-topbar.component.js", "format-version": 4, "code-base-name": "https://github.com/Kishore6753/todomvc.git:master", "knowledge_revision": 1044, "git_revision": "95ade963e1062e27963c51b1693289efca5822f4", "revision_history": [{"1044": "95ade963e1062e27963c51b1693289efca5822f4"}, {"1044": "95ade963e1062e27963c51b1693289efca5822f4"}], "file_id": 906}